MANIFEST.in
README.md
README.rst
license.txt
setup.py
iml_common/__init__.py
iml_common/scm_version.py
iml_common.egg-info/PKG-INFO
iml_common.egg-info/SOURCES.txt
iml_common.egg-info/dependency_links.txt
iml_common.egg-info/top_level.txt
iml_common/blockdevices/__init__.py
iml_common/blockdevices/blockdevice.py
iml_common/blockdevices/blockdevice_linux.py
iml_common/blockdevices/blockdevice_lvm_volume.py
iml_common/blockdevices/blockdevice_zfs.py
iml_common/filesystems/__init__.py
iml_common/filesystems/filesystem.py
iml_common/filesystems/filesystem_ldiskfs.py
iml_common/filesystems/filesystem_zfs.py
iml_common/lib/__init__.py
iml_common/lib/agent_rpc.py
iml_common/lib/date_time.py
iml_common/lib/evaluator.py
iml_common/lib/exception_sandbox.py
iml_common/lib/firewall_control.py
iml_common/lib/name_value_list.py
iml_common/lib/ntp.py
iml_common/lib/package_version_info.py
iml_common/lib/service_control.py
iml_common/lib/shell.py
iml_common/lib/util.py
iml_common/test/__init__.py
iml_common/test/command_capture_testcase.py
iml_common/test/iml_unit_testcase.py