Metadata-Version: 1.1
Name: iml-common
Version: 1.4.1
Summary: Common library used by multiple IML components
Home-page: https://pypi.python.org/pypi/iml-common
Author: Intel Corporation
Author-email: iml@intel.com
License: MIT
Keywords: IML lustre high-availability
Platform: UNKNOWN
Classifier: Development Status :: 5 - Production/Stable
Classifier: License :: OSI Approved :: MIT License
Classifier: Programming Language :: Python :: 2
Classifier: Programming Language :: Python :: 2.7
